[
  {
    "title": "A new day at DEQ and DNRC",
    "date": "2021-01-08T13:03:58",
    "link": "https://montanafreepress.org/2021/01/08/a-new-day-at-deq-and-dnrc/",
    "status": "publish",
    "tags": {
      "nodes": [
        {
          "name": "2021 Legislature"
        },
        {
          "name": "Amanda Kaster"
        },
        {
          "name": "Chris Dorrington"
        },
        {
          "name": "Department of Environmental Quality"
        },
        {
          "name": "Department of Natural Resources and Conservation"
        },
        {
          "name": "DEQ"
        },
        {
          "name": "DNRC"
        },
        {
          "name": "Greg Gianforte"
        }
      ]
    },
    "featuredImage": {
      "node": {
        "link": "https://montanafreepress.org/2020/10/13/the-statesman-and-the-mogul/cramer_governor13/"
      }
    },
    "categories": {
      "nodes": [
        {
          "name": "Environment"
        },
        {
          "name": "Government"
        },
        {
          "name": "News"
        }
      ]
    }
  },
  {
    "title": "Legislature announces lawmaker’s positive COVID test",
    "date": "2021-01-07T21:19:04",
    "link": "https://montanafreepress.org/2021/01/07/legislature-announces-lawmakers-positive-covid-test/",
    "status": "publish",
    "tags": {
      "nodes": [
        {
          "name": "2021 Legislature"
        },
        {
          "name": "Briefs"
        },
        {
          "name": "coronavirus"
        },
        {
          "name": "COVID-19"
        },
        {
          "name": "David Bedey"
        },
        {
          "name": "Kyle Schmauch"
        }
      ]
    },
    "featuredImage": null,
    "categories": {
      "nodes": [
        {
          "name": "Coronavirus"
        },
        {
          "name": "Montana Legislature"
        },
        {
          "name": "News"
        }
      ]
    }
  },
  {
    "title": "Gianforte budget calls for multiple tax reductions",
    "date": "2021-01-07T18:38:28",
    "link": "https://montanafreepress.org/2021/01/07/gianforte-budget-calls-for-multiple-tax-relief-measures/",
    "status": "publish",
    "tags": {
      "nodes": [
        {
          "name": "2021 Legislature"
        },
        {
          "name": "Budget"
        },
        {
          "name": "Greg Gianforte"
        },
        {
          "name": "Kurt Alme"
        }
      ]
    },
    "featuredImage": {
      "node": {
        "link": "https://montanafreepress.org/2020/12/11/rules-maneuvers-hint-at-a-potential-hardline-coup-in-the-house/montana-capitol_-adams_1200x675/"
      }
    },
    "categories": {
      "nodes": [
        {
          "name": "Economy"
        },
        {
          "name": "Government"
        },
        {
          "name": "Montana Legislature"
        },
        {
          "name": "News"
        },
        {
          "name": "Taxes"
        }
      ]
    }
  },
  {
    "title": "Gianforte signals support for state pay plan proposal",
    "date": "2021-01-06T17:24:26",
    "link": "https://montanafreepress.org/2021/01/06/gianforte-signals-support-for-state-pay-plan-proposal/",
    "status": "publish",
    "tags": {
      "nodes": [
        {
          "name": "2021 Legislature"
        },
        {
          "name": "Greg Gianforte"
        },
        {
          "name": "House Appropriations Committee"
        },
        {
          "name": "House Bill 13"
        },
        {
          "name": "Kurt Alme"
        }
      ]
    },
    "featuredImage": {
      "node": {
        "link": "https://montanafreepress.org/2021/01/06/gianforte-signals-support-for-state-pay-plan-proposal/capitol-dome_-adobe-stock/"
      }
    },
    "categories": {
      "nodes": [
        {
          "name": "Economy"
        },
        {
          "name": "Government"
        },
        {
          "name": "Labor"
        },
        {
          "name": "Montana Legislature"
        },
        {
          "name": "News"
        }
      ]
    }
  },
  {
    "title": "Pro-public health and anti-mask contingents hold concurrent rallies on opening day",
    "date": "2021-01-04T18:04:29",
    "link": "https://montanafreepress.org/2021/01/04/pro-public-health-and-anti-mask-contingents-face-off-on-opening-day/",
    "status": "publish",
    "tags": {
      "nodes": [
        {
          "name": "2021 Legislature"
        },
        {
          "name": "67th legislature"
        },
        {
          "name": "coronavirus"
        },
        {
          "name": "COVID-19"
        },
        {
          "name": "masks"
        }
      ]
    },
    "featuredImage": {
      "node": {
        "link": "https://montanafreepress.org/2021/01/04/pro-public-health-and-anti-mask-contingents-face-off-on-opening-day/pro-mask-protester/"
      }
    },
    "categories": {
      "nodes": [
        {
          "name": "Coronavirus"
        },
        {
          "name": "Government"
        },
        {
          "name": "Montana Legislature"
        },
        {
          "name": "News"
        },
        {
          "name": "Public Health"
        },
        {
          "name": "Public Safety"
        }
      ]
    }
  },
  {
    "title": "2021 Legislature convenes in a crowded Capitol",
    "date": "2021-01-04T17:52:52",
    "link": "https://montanafreepress.org/2021/01/04/2021-legislature-convenes-in-a-crowded-capitol/",
    "status": "publish",
    "tags": {
      "nodes": [
        {
          "name": "2021 Legislature"
        },
        {
          "name": "Wylie Galt"
        }
      ]
    },
    "featuredImage": {
      "node": {
        "link": "https://montanafreepress.org/2021/01/04/2021-legislature-convenes-in-a-crowded-capitol/house-floor-on-day-1/"
      }
    },
    "categories": {
      "nodes": [
        {
          "name": "Coronavirus"
        },
        {
          "name": "Government"
        },
        {
          "name": "Montana Legislature"
        },
        {
          "name": "News"
        },
        {
          "name": "Public Health"
        }
      ]
    }
  },
  {
    "title": "The stories of 2020",
    "date": "2021-01-02T13:22:16",
    "link": "https://montanafreepress.org/2021/01/02/the-stories-of-2020/",
    "status": "publish",
    "tags": {
      "nodes": [
        {
          "name": "2021 Legislature"
        },
        {
          "name": "coronavirus"
        },
        {
          "name": "COVID-19"
        },
        {
          "name": "CSKT Water Compact"
        },
        {
          "name": "Greg Gianforte"
        },
        {
          "name": "Montana Free Press"
        },
        {
          "name": "Public Lands"
        },
        {
          "name": "Shared State"
        },
        {
          "name": "Steve Bullock"
        },
        {
          "name": "Steve Daines"
        }
      ]
    },
    "featuredImage": {
      "node": {
        "link": "https://montanafreepress.org/2021/01/02/the-stories-of-2020/rearview-mirror/"
      }
    },
    "categories": {
      "nodes": [
        {
          "name": "News"
        }
      ]
    }
  },
  {
    "title": "Lawmakers anxious, excited ahead of 2021 session",
    "date": "2020-12-30T10:05:00",
    "link": "https://montanafreepress.org/2020/12/30/lawmakers-anxious-excited-ahead-of-2021-session/",
    "status": "publish",
    "tags": {
      "nodes": [
        {
          "name": "2021 Legislature"
        },
        {
          "name": "coronavirus"
        },
        {
          "name": "COVID-19"
        },
        {
          "name": "Democrats"
        },
        {
          "name": "Public health"
        },
        {
          "name": "Republicans"
        },
        {
          "name": "state government"
        }
      ]
    },
    "featuredImage": {
      "node": {
        "link": "https://montanafreepress.org/2020/12/30/lawmakers-anxious-excited-ahead-of-2021-session/montana-capitol_adobe-stock/"
      }
    },
    "categories": {
      "nodes": [
        {
          "name": "Coronavirus"
        },
        {
          "name": "Government"
        },
        {
          "name": "Montana Legislature"
        },
        {
          "name": "News"
        },
        {
          "name": "Public Health"
        }
      ]
    }
  },
  {
    "title": "Legislative session will be in-person and virtual, per Rules Committee",
    "date": "2020-12-16T18:17:49",
    "link": "https://montanafreepress.org/2020/12/16/legislative-session-will-be-in-person-and-virtual-per-rules-committee/",
    "status": "publish",
    "tags": {
      "nodes": [
        {
          "name": "2021 Legislature"
        },
        {
          "name": "coronavirus"
        },
        {
          "name": "COVID-19"
        },
        {
          "name": "Montana Legislature"
        },
        {
          "name": "state government"
        }
      ]
    },
    "featuredImage": {
      "node": {
        "link": "https://montanafreepress.org/2020/11/06/how-will-the-gop-spend-its-mandate/montana-capitol-dome-1200x675/"
      }
    },
    "categories": {
      "nodes": [
        {
          "name": "Coronavirus"
        },
        {
          "name": "Government"
        },
        {
          "name": "Montana Legislature"
        },
        {
          "name": "News"
        },
        {
          "name": "Public Health"
        }
      ]
    }
  },
  {
    "title": "Rules maneuvers hint at a potential hardline coup in the House",
    "date": "2020-12-11T15:17:54",
    "link": "https://montanafreepress.org/2020/12/11/rules-maneuvers-hint-at-a-potential-hardline-coup-in-the-house/",
    "status": "publish",
    "tags": {
      "nodes": [
        {
          "name": "2021 Legislature"
        },
        {
          "name": "Kim Abbott"
        },
        {
          "name": "Llew Jones"
        },
        {
          "name": "Matt Regier"
        },
        {
          "name": "Matthew Monforton"
        },
        {
          "name": "Solutions Caucus"
        },
        {
          "name": "Wylie Galt"
        }
      ]
    },
    "featuredImage": {
      "node": {
        "link": "https://montanafreepress.org/2020/12/11/rules-maneuvers-hint-at-a-potential-hardline-coup-in-the-house/montana-capitol_-adams_1200x675/"
      }
    },
    "categories": {
      "nodes": [
        {
          "name": "Coronavirus"
        },
        {
          "name": "Government"
        },
        {
          "name": "Montana Legislature"
        },
        {
          "name": "News"
        },
        {
          "name": "Politics"
        }
      ]
    }
  },
  {
    "title": "Nipped in the bud?",
    "date": "2020-12-08T08:32:14",
    "link": "https://montanafreepress.org/2020/12/08/nipped-in-the-bud-recreational-marijuana-opposition-red-state/",
    "status": "publish",
    "tags": {
      "nodes": [
        {
          "name": "2021 Legislature"
        },
        {
          "name": "Derek Skees"
        },
        {
          "name": "marijuana legalization"
        }
      ]
    },
    "featuredImage": {
      "node": {
        "link": "https://montanafreepress.org/2020/12/08/nipped-in-the-bud-recreational-marijuana-opposition-red-state/legal-pot-on-shelves/"
      }
    },
    "categories": {
      "nodes": [
        {
          "name": "Drug Policy"
        },
        {
          "name": "Elections"
        },
        {
          "name": "Government"
        },
        {
          "name": "Montana Legislature"
        },
        {
          "name": "News"
        }
      ]
    }
  },
  {
    "title": "Gianforte holds first press conference",
    "date": "2020-12-04T17:26:25",
    "link": "https://montanafreepress.org/2020/12/04/gianforte-holds-first-press-conference/",
    "status": "publish",
    "tags": {
      "nodes": [
        {
          "name": "2021 Legislature"
        },
        {
          "name": "Greg Gianforte"
        },
        {
          "name": "Montana Governor"
        }
      ]
    },
    "featuredImage": {
      "node": {
        "link": "https://montanafreepress.org/2020/11/17/gianforte-begins-transition-with-advisory-appointments/2020_greg-gianforte_ball-cap/"
      }
    },
    "categories": {
      "nodes": [
        {
          "name": "Government"
        },
        {
          "name": "News"
        },
        {
          "name": "Politics"
        }
      ]
    }
  },
  {
    "title": "Gianforte picks ‘full-spectrum conservative’ as lead lawyer",
    "date": "2020-12-01T09:22:18",
    "link": "https://montanafreepress.org/2020/12/01/gianforte-picks-full-spectrum-conservative-as-lead-lawyer/",
    "status": "publish",
    "tags": {
      "nodes": [
        {
          "name": "2021 Legislature"
        },
        {
          "name": "Anita Milanovich"
        },
        {
          "name": "Greg Gianforte"
        }
      ]
    },
    "featuredImage": {
      "node": {
        "link": "https://montanafreepress.org/2020/12/01/gianforte-picks-full-spectrum-conservative-as-lead-lawyer/anita/"
      }
    },
    "categories": {
      "nodes": [
        {
          "name": "Government"
        },
        {
          "name": "Montana Legislature"
        },
        {
          "name": "News"
        }
      ]
    }
  },
  {
    "title": "Gianforte names U.S. Attorney as budget director",
    "date": "2020-11-24T14:22:20",
    "link": "https://montanafreepress.org/2020/11/24/gianforte-names-u-s-attorney-as-budget-director/",
    "status": "publish",
    "tags": {
      "nodes": [
        {
          "name": "2021 Legislature"
        },
        {
          "name": "2021 session"
        },
        {
          "name": "budget director"
        },
        {
          "name": "Greg Gianforte"
        },
        {
          "name": "Kurt Alme"
        }
      ]
    },
    "featuredImage": {
      "node": {
        "link": "https://montanafreepress.org/2020/11/24/gianforte-names-u-s-attorney-as-budget-director/kurt-alme_mug_1200x675/"
      }
    },
    "categories": {
      "nodes": [
        {
          "name": "Government"
        },
        {
          "name": "News"
        }
      ]
    }
  },
  {
    "title": "COVID and the Capitol",
    "date": "2020-11-19T14:30:57",
    "link": "https://montanafreepress.org/2020/11/19/covid-and-the-capitol/",
    "status": "publish",
    "tags": {
      "nodes": [
        {
          "name": "2021 Legislature"
        },
        {
          "name": "2021 session"
        },
        {
          "name": "Drenda Niemann"
        },
        {
          "name": "Kim Abbott"
        },
        {
          "name": "Lewis and Clark County"
        },
        {
          "name": "Mark Blasdel"
        },
        {
          "name": "Montana Capitol"
        },
        {
          "name": "Montana GOP"
        },
        {
          "name": "Montana Legislature"
        },
        {
          "name": "Montana Republicans"
        }
      ]
    },
    "featuredImage": {
      "node": {
        "link": "https://montanafreepress.org/2020/11/19/covid-and-the-capitol/2020-11_house-gop-caucus-on-floor/"
      }
    },
    "categories": {
      "nodes": [
        {
          "name": "Coronavirus"
        },
        {
          "name": "Government"
        },
        {
          "name": "Montana Legislature"
        },
        {
          "name": "News"
        },
        {
          "name": "Public Health"
        }
      ]
    }
  },
  {
    "title": "Newly elected lawmakers pick leaders for 2021 session",
    "date": "2020-11-18T16:33:38",
    "link": "https://montanafreepress.org/2020/11/18/newly-elected-lawmakers-pick-leaders-for-2021-session/",
    "status": "publish",
    "tags": {
      "nodes": [
        {
          "name": "2021 Legislature"
        },
        {
          "name": "2021 session"
        },
        {
          "name": "Mark Blasdel"
        },
        {
          "name": "Montana Legislature"
        },
        {
          "name": "Wylie Galt"
        }
      ]
    },
    "featuredImage": {
      "node": {
        "link": "https://montanafreepress.org/2020/11/18/newly-elected-lawmakers-pick-leaders-for-2021-session/2020-11_mtgop-house-leaders/"
      }
    },
    "categories": {
      "nodes": [
        {
          "name": "Government"
        },
        {
          "name": "Montana Legislature"
        },
        {
          "name": "News"
        }
      ]
    }
  },
  {
    "title": "Politicos explain Montana’s red wave",
    "date": "2020-11-11T18:41:18",
    "link": "https://montanafreepress.org/2020/11/11/politicos-explain-montanas-red-wave/",
    "status": "publish",
    "tags": {
      "nodes": [
        {
          "name": "2020 Election"
        },
        {
          "name": "2020 Elections"
        },
        {
          "name": "2021 Legislature"
        },
        {
          "name": "2021 session"
        }
      ]
    },
    "featuredImage": {
      "node": {
        "link": "https://montanafreepress.org/2020/11/11/politicos-explain-montanas-red-wave/elephant-outweighs-donkey-1200x675/"
      }
    },
    "categories": {
      "nodes": [
        {
          "name": "Elections"
        },
        {
          "name": "Politics"
        }
      ]
    }
  },
  {
    "title": "How will the GOP spend its mandate?",
    "date": "2020-11-06T17:39:49",
    "link": "https://montanafreepress.org/2020/11/06/how-will-the-gop-spend-its-mandate/",
    "status": "publish",
    "tags": {
      "nodes": [
        {
          "name": "2020 Election"
        },
        {
          "name": "2020 Elections"
        },
        {
          "name": "2021 Legislature"
        },
        {
          "name": "2021 session"
        },
        {
          "name": "Election 2020"
        },
        {
          "name": "Elections 2020"
        },
        {
          "name": "Greg Gianforte"
        },
        {
          "name": "Montana GOP"
        },
        {
          "name": "Montana Republicans"
        },
        {
          "name": "Wylie Galt"
        }
      ]
    },
    "featuredImage": {
      "node": {
        "link": "https://montanafreepress.org/2020/11/06/how-will-the-gop-spend-its-mandate/montana-capitol-dome-1200x675/"
      }
    },
    "categories": {
      "nodes": [
        {
          "name": "Elections"
        },
        {
          "name": "Government"
        },
        {
          "name": "Montana Legislature"
        },
        {
          "name": "News"
        }
      ]
    }
  },
  {
    "title": "Shared State",
    "date": "2020-11-05T17:14:10",
    "link": "https://montanafreepress.org/2020/11/05/shared-state-ep-10-where-do-we-go-from-here/",
    "status": "publish",
    "tags": {
      "nodes": [
        {
          "name": "2020 Elections"
        },
        {
          "name": "2021 Legislature"
        },
        {
          "name": "2021 session"
        },
        {
          "name": "Corin Cates Carney"
        },
        {
          "name": "John S. Adams"
        },
        {
          "name": "Montana election results"
        },
        {
          "name": "Montana Politics"
        },
        {
          "name": "Nicky Oulette"
        },
        {
          "name": "Podcast"
        },
        {
          "name": "podcast-player"
        }
      ]
    },
    "featuredImage": {
      "node": {
        "link": "https://montanafreepress.org/montana-2020-election/shared-state/shared-state-web-banner/"
      }
    },
    "categories": {
      "nodes": [
        {
          "name": "News"
        },
        {
          "name": "Podcast"
        },
        {
          "name": "Politics"
        }
      ]
    }
  },
  {
    "title": "How Montanans voted, precinct by precinct",
    "date": "2020-11-05T16:41:57",
    "link": "https://montanafreepress.org/2020/11/05/how-montanans-voted-precinct-by-precinct/",
    "status": "publish",
    "tags": {
      "nodes": [
        {
          "name": "2020 Election"
        },
        {
          "name": "2021 Legislature"
        },
        {
          "name": "2021 session"
        },
        {
          "name": "Montana election results"
        }
      ]
    },
    "featuredImage": {
      "node": {
        "link": "https://montanafreepress.org/2020/11/05/how-montanans-voted-precinct-by-precinct/image-3/"
      }
    },
    "categories": {
      "nodes": [
        {
          "name": "Elections"
        },
        {
          "name": "News"
        },
        {
          "name": "Politics"
        }
      ]
    }
  },
  {
    "title": "Lawmakers spar over legislative rules",
    "date": "2020-09-17T17:12:20",
    "link": "https://montanafreepress.org/2020/09/17/lawmakers-spar-over-legislative-rules/",
    "status": "publish",
    "tags": {
      "nodes": [
        {
          "name": "2021 Legislature"
        },
        {
          "name": "2021 session"
        },
        {
          "name": "Fred Thomas"
        },
        {
          "name": "Joint senate and house rules committee"
        },
        {
          "name": "Kim Abbott"
        },
        {
          "name": "Mike Meloy"
        },
        {
          "name": "Montana Legislature"
        }
      ]
    },
    "featuredImage": {
      "node": {
        "link": "https://montanafreepress.org/2020/09/17/lawmakers-spar-over-legislative-rules/fred-thomas_freddy-monares-um-legislative-news-service/"
      }
    },
    "categories": {
      "nodes": [
        {
          "name": "Coronavirus"
        },
        {
          "name": "Government"
        },
        {
          "name": "Montana Legislature"
        },
        {
          "name": "News"
        }
      ]
    }
  },
  {
    "title": "Analysts say state budget looks OK for next year",
    "date": "2020-08-12T17:08:56",
    "link": "https://montanafreepress.org/2020/08/12/analysts-say-state-budget-looks-ok-for-next-year/",
    "status": "publish",
    "tags": {
      "nodes": [
        {
          "name": "2021 Legislature"
        },
        {
          "name": "2021 session"
        },
        {
          "name": "Budget Stabilization Reserve Fund"
        },
        {
          "name": "COVID-19"
        },
        {
          "name": "Legislature"
        },
        {
          "name": "state budget"
        },
        {
          "name": "Steve Bullock"
        }
      ]
    },
    "featuredImage": {
      "node": {
        "link": "https://montanafreepress.org/2020/11/06/how-will-the-gop-spend-its-mandate/montana-capitol-dome-1200x675/"
      }
    },
    "categories": {
      "nodes": [
        {
          "name": "Coronavirus"
        },
        {
          "name": "Economy"
        },
        {
          "name": "Government"
        },
        {
          "name": "Montana Legislature"
        },
        {
          "name": "News"
        },
        {
          "name": "Taxes"
        }
      ]
    }
  },
  {
    "title": "Primary results, and the path to November",
    "date": "2020-06-09T10:06:43",
    "link": "https://montanafreepress.org/2020/06/09/2020-primary-results-and-a-preview-of-the-path-to-november/",
    "status": "publish",
    "tags": {
      "nodes": [
        {
          "name": "2020 Election"
        },
        {
          "name": "2020 Primary"
        },
        {
          "name": "2021 Legislature"
        },
        {
          "name": "2021 session"
        },
        {
          "name": "Montana Lowdown"
        }
      ]
    },
    "featuredImage": {
      "node": {
        "link": "https://montanafreepress.org/2020/06/09/2020-primary-results-and-a-preview-of-the-path-to-november/ballot-and-pen/"
      }
    },
    "categories": {
      "nodes": [
        {
          "name": "Elections"
        },
        {
          "name": "News"
        },
        {
          "name": "Podcast"
        },
        {
          "name": "Politics"
        }
      ]
    }
  },
  {
    "title": "Primary battles between Solutions Caucus legislators and right-flanking challengers produced a mixed bag",
    "date": "2020-06-03T16:56:36",
    "link": "https://montanafreepress.org/2020/06/03/primary-battles-between-solutions-caucus-legislators-and-right-flanking-challengers-produced-a-mixed-bag/",
    "status": "publish",
    "tags": {
      "nodes": [
        {
          "name": "2021 Legislature"
        },
        {
          "name": "2021 session"
        },
        {
          "name": "Montana Legislature"
        },
        {
          "name": "Solutions Caucus"
        }
      ]
    },
    "featuredImage": {
      "node": {
        "link": "https://montanafreepress.org/2020/05/30/republican-factions-vie-for-legislative-control/elephants-mt/"
      }
    },
    "categories": {
      "nodes": [
        {
          "name": "Elections"
        },
        {
          "name": "News"
        },
        {
          "name": "Politics"
        }
      ]
    }
  },
  {
    "title": "Republican factions vie for legislative control",
    "date": "2020-05-30T14:49:37",
    "link": "https://montanafreepress.org/2020/05/30/republican-factions-vie-for-legislative-control/",
    "status": "publish",
    "tags": {
      "nodes": [
        {
          "name": ".38 special"
        },
        {
          "name": "2020 Elections"
        },
        {
          "name": "2020 Primary"
        },
        {
          "name": "2021 Legislature"
        },
        {
          "name": "2021 session"
        },
        {
          "name": "Montana Legislature"
        },
        {
          "name": "Solutions Caucus"
        }
      ]
    },
    "featuredImage": {
      "node": {
        "link": "https://montanafreepress.org/2020/05/30/republican-factions-vie-for-legislative-control/elephants-mt/"
      }
    },
    "categories": {
      "nodes": [
        {
          "name": "Elections"
        },
        {
          "name": "Government"
        },
        {
          "name": "Montana Legislature"
        },
        {
          "name": "News"
        },
        {
          "name": "Podcast"
        },
        {
          "name": "Politics"
        }
      ]
    }
  }
]